plumbersdk.py
plumbersdk-0.0.1.dist-info/LICENSE
plumbersdk-0.0.1.dist-info/METADATA
plumbersdk-0.0.1.dist-info/WHEEL
plumbersdk-0.0.1.dist-info/top_level.txt
plumbersdk-0.0.1.dist-info/RECORD
