Metadata-Version: 2.1
Name: plumbersdk
Version: 0.0.1
Summary: Python SDK for interacting with the sidecar
Home-page: https://github.com/pypa/sampleproject
Author: Bert Verstraete
Author-email: bert.verstraete@ugent.be
License: UNKNOWN
Project-URL: Bug Tracker, https://github.com/pypa/sampleproject/issues
Platform: UNKNOWN
Classifier: Programming Language :: Python :: 3
Classifier: License :: OSI Approved :: MIT License
Classifier: Operating System :: OS Independent
Requires-Python: >=3.6
